gologin_api/__init__.py
gologin_api/api.py
gologin_api-0.1.0.dist-info/METADATA
gologin_api-0.1.0.dist-info/WHEEL
gologin_api-0.1.0.dist-info/top_level.txt
gologin_api-0.1.0.dist-info/RECORD
