Metadata-Version: 2.4
Name: gologin_api
Version: 0.1.0
Summary: Tiny wrapper for GoLogin and fingerprint API via Google Apps Script
Home-page: https://github.com/yourusername/gologin_api
Author: Tu Hoang
Project-URL: Homepage, https://github.com/yourusername/gologin_api
Requires-Python: >=3.6
Requires-Dist: requests>=2.0
Dynamic: author
Dynamic: home-page
Dynamic: requires-python
